[{"id":589687,"node":"经济","node_url":"https://www.v2ex.com/go/eco","node_image":"/static/img/node_mini.png","description":"<p>不知道是不是因为最近某行政区的新闻看的比较多</p>\n","url":"https://www.v2ex.com/t/589687","replies":98,"created_ts":1565139867,"created":"09:04:27","title":"开始觉得未来经济形势会很严峻","author":"marcX","author_url":"https://www.v2ex.com/u/marcX","author_image":"//cdn.v2ex.com/avatar/291c/6bcf/408297_mini.png?m=1556765392"},{"id":589786,"node":"问与答","node_url":"https://www.v2ex.com/go/qna","node_image":"//cdn.v2ex.com/navatar/c20a/d4d7/12_mini.png?m=1564402099","description":"<p>以前一直自黑因为程序员，所以找不着女朋友。。\n没想到就真的找不着。。</p>\n<p>统计一下 v 友单身比例多少</p>\n<p>单身回复 1</p>\n<p>有对象（包括已婚）回复 2</p>\n<p>单身可以继续回复</p>\n<p>有喜欢的人或有人喜欢你回复 3</p>\n<p>没有喜欢的人也没人喜欢你回复 4</p>\n","url":"https://www.v2ex.com/t/589786","replies":88,"created_ts":1565152809,"created":"12:40:09","title":"做个统计，到底有对象的有多少人？","author":"tmac6740","author_url":"https://www.v2ex.com/u/tmac6740","author_image":"//cdn.v2ex.com/avatar/806a/141d/170063_mini.png?m=1484050997"},{"id":589713,"node":"问与答","node_url":"https://www.v2ex.com/go/qna","node_image":"//cdn.v2ex.com/navatar/c20a/d4d7/12_mini.png?m=1564402099","description":"","url":"https://www.v2ex.com/t/589713","replies":83,"created_ts":1565143841,"created":"10:10:41","title":"今天 你们给对象送什么礼物了","author":"zaiyund","author_url":"https://www.v2ex.com/u/zaiyund","author_image":"//cdn.v2ex.com/avatar/5b32/acfa/396253_mini.png?m=1565151537"},{"id":589907,"node":"程序员","node_url":"https://www.v2ex.com/go/programmer","node_image":"//cdn.v2ex.com/navatar/94f6/d7e0/300_mini.png?m=1565073122","description":"<p>估计最近有大公司发来 online test，鉴于没刷过 leetcode 之类的，心里很慌</p>\n<p>有没有可以有偿帮做题的，100 块 1 道题？</p>\n","url":"https://www.v2ex.com/t/589907","replies":76,"created_ts":1565172704,"created":"18:11:44","title":"有没有在线帮忙做算法题的服务","author":"shuson","author_url":"https://www.v2ex.com/u/shuson","author_image":"//cdn.v2ex.com/avatar/2562/e666/29065_mini.png?m=1351566403"},{"id":589798,"node":"奇思妙想","node_url":"https://www.v2ex.com/go/ideas","node_image":"//cdn.v2ex.com/navatar/6353/8fe6/519_mini.png?m=1537099731","description":"<p>明天考科目三，刚才教练说打点费的事，两个档次：<br/>\n档次 1：500 元，考官不会干扰你，给你使坏，全屏自己真本事考试；<br/>\n档次 2：1200 元，全程提醒，保证在人工监考分数上，不会扣分。<br/>\n如果这次不过，考一次都要交一次，愁人……</p>\n","url":"https://www.v2ex.com/t/589798","replies":67,"created_ts":1565156159,"created":"13:35:59","title":"哎，什么时候驾考才能全电脑监考啊！","author":"weiruanniubi","author_url":"https://www.v2ex.com/u/weiruanniubi","author_image":"//cdn.v2ex.com/avatar/2122/1c8b/432867_mini.png?m=1564464733"},{"id":589968,"node":"程序员","node_url":"https://www.v2ex.com/go/programmer","node_image":"//cdn.v2ex.com/navatar/94f6/d7e0/300_mini.png?m=1565073122","description":"<p>如题，电脑是笔记本，自带 8G 内存，我自己又加了一根 8G 内存条，威刚京东旗舰店买的，安装后 Windows 可以自动识别到，系统也显示 16G 内存，CPU-Z 查看也能正确识别，显示双通道。老实说，加上内存后，我并没有感觉自己电脑性能有多大提升，这样一直用了半年。直到今天，准备运行一个比较大的 java 项目，一直跑不起来，说是内存不足，无法创建 java 虚拟机，但是任务管理器显示内存占用才 48%，，我：黑人问号？？？然后我尝试 Chrome 多开标签页，内存占用 50%的时候，各种崩溃就来了，chrome 显示内存不足，后台其他程序也崩溃了。\n求问大家，这是咋回事啊？？我用 Windows 自带的内存诊断工具跑了一下，内存检测结果正常。CPU-Z 也可以争取识别。我的 Windows 版本：Windows 10 1903\n插槽一\n<a href=\"https://imgchr.com/i/eokeQe\" rel=\"nofollow\"><img alt=\"eokeQe.png\" src=\"https://s2.ax1x.com/2019/08/07/eokeQe.png\"/></a>\n插槽二\n<a href=\"https://imgchr.com/i/eok3Jf\" rel=\"nofollow\"><img alt=\"eok3Jf.png\" src=\"https://s2.ax1x.com/2019/08/07/eok3Jf.png\"/></a>\n求问大家，这是啥问题，目前内存不足已经严重影响到我敲代码了。。。</p>\n","url":"https://www.v2ex.com/t/589968","replies":62,"created_ts":1565190356,"created":"23:05:56","title":"电脑 16G 内存，占用 50%后提示内存不足","author":"godlovesxcjtest","author_url":"https://www.v2ex.com/u/godlovesxcjtest","author_image":"//cdn.v2ex.com/gravatar/f32566dcdbefebbf306a5b102193185c?s=24&d=retro"},{"id":589710,"node":"问与答","node_url":"https://www.v2ex.com/go/qna","node_image":"//cdn.v2ex.com/navatar/c20a/d4d7/12_mini.png?m=1564402099","description":"1. 最常见的方式大概是趴在桌子上，但是枕着胳膊的话很不舒服，睡觉起来后胳膊都麻了；枕着抱枕也不是很舒服，夏天容易起汗，或者说我自己的抱枕不够舒服？<br />2. 有看到小伙伴直坐着靠在座椅上，头微向后仰的方式的。<br />3. 也有女生买了个建议折叠“床”放在公司的，这种就不考虑了。<br /><br />v 友们都是怎么午休的？","url":"https://www.v2ex.com/t/589710","replies":62,"created_ts":1565143648,"created":"10:07:28","title":"你们中午午休都是怎么休息的？","author":"nikolausliu","author_url":"https://www.v2ex.com/u/nikolausliu","author_image":"//cdn.v2ex.com/avatar/a270/81f6/352971_mini.png?m=1545707600"},{"id":589918,"node":"职场话题","node_url":"https://www.v2ex.com/go/career","node_image":"//cdn.v2ex.com/navatar/4ea0/6fbc/770_mini.png?m=1564717604","description":"<p>有点好奇，公司配备的开发电脑，你们是怎么维护的？</p>\n<p>比如贴个透明膜？ 买个专门装他的包包？</p>\n","url":"https://www.v2ex.com/t/589918","replies":60,"created_ts":1565175847,"created":"19:04:07","title":"公司配给你的电脑，你是怎么维护的？","author":"smallgoogle","author_url":"https://www.v2ex.com/u/smallgoogle","author_image":"//cdn.v2ex.com/avatar/b6ea/81a9/185942_mini.png?m=1544125297"},{"id":589737,"node":"职场话题","node_url":"https://www.v2ex.com/go/career","node_image":"//cdn.v2ex.com/navatar/4ea0/6fbc/770_mini.png?m=1564717604","description":"<p>楼主六月份毕业  普通本科  前端码农一枚  目前在合肥一家 IT 公司上班 五月份入职  到现在加上实习经验也有一年了  之前选择合肥原因是因为家里要求  两个姐姐都在合肥 房子也买在这边的  父母希望今年待在合肥（怕我没有社会阅历被骗 天下父母心 在合肥有家人在这边不担心）明年随便我去哪\n目前的状态是 965 包住 五险 转正到手只有 3000 块（真的很少很少 别嘲讽我 合肥应届薪资只有这么多）目前在准备阶段（知识储备＋目标城市）  对别的城市也不了解  我心目中 优先级是江浙一带二线城市 武汉 上海 广东一带 北京  大家有什么建议吗？</p>\n","url":"https://www.v2ex.com/t/589737","replies":59,"created_ts":1565145830,"created":"10:43:50","title":"作为一名 IT 从业者 未来到底该去哪座城市比较好呢？","author":"nonrerrorYhd","author_url":"https://www.v2ex.com/u/nonrerrorYhd","author_image":"//cdn.v2ex.com/avatar/c9a4/540e/423663_mini.png?m=1561112195"},{"id":589879,"node":"程序员","node_url":"https://www.v2ex.com/go/programmer","node_image":"//cdn.v2ex.com/navatar/94f6/d7e0/300_mini.png?m=1565073122","description":"<p>最近很头疼，不知道该怎么办，也不知道自己真正想要什么，于是来 V2 上吐吐槽。</p>\n<p>这是我昨天写的一篇发牢骚的文章，原因大抵都写在里面了：<a href=\"https://blog.huangluyu.com/2019/08/06/%E6%88%91%E7%9A%84%E5%8E%8B%E5%8A%9B%E4%BB%8E%E4%BD%95%E8%80%8C%E6%9D%A5%EF%BC%9F/\" rel=\"nofollow\">我的压力从何而来？</a></p>\n<p>上海买房总归也买不起，回去是肯定得回去的。</p>\n<ul>\n<li>\n<p>回二线城市一定代表没有发展吗？（大环境氛围一定差吗？）</p>\n</li>\n<li>\n<p>程序员的高薪能持续维持下去吗？（我看不懂高薪的原因。）</p>\n</li>\n</ul>\n","url":"https://www.v2ex.com/t/589879","replies":58,"created_ts":1565167759,"created":"16:49:19","title":"七夕，问个沉痛的话题：家庭和发展如何选？","author":"huangdaxian","author_url":"https://www.v2ex.com/u/huangdaxian","author_image":"//cdn.v2ex.com/gravatar/a4d77c0fb6089f442ca339ba461a0723?s=24&d=retro"},{"id":589872,"node":"问与答","node_url":"https://www.v2ex.com/go/qna","node_image":"//cdn.v2ex.com/navatar/c20a/d4d7/12_mini.png?m=1564402099","description":"<p>正值七夕，发点感慨给 V 友们吃吃瓜😇。</p>\n<p>先说下自身情况，苏州土著，92，男，双非普通本科财务会计学，父母工行在职，在姑苏区和园区有 2 套房，毕业后在一家上市光伏企业做财务，从 2K 做起😒，2 年后时来运转派驻到海外工厂做成本核算，每月加补贴能拿到 14K😍（当然在 V 坛只能算是毕业起步），在外面呆了两年半后今年回国跳槽了，因为国内总部开的太低了，一直在外面也不方便，重新找了其他行业的上市制造公司做财务课长，9K 的水平，这个数字在苏州也只能算是普通，财务毕竟现在打翻了😣，自己也没有什么含金量高的证书。</p>\n<p>上周脑抽注册了个世纪佳缘🤯，注册完就醒了，删除了事，可是隔天电话就过来了，微信电话什么聊了一会儿，让我下班后去聊聊，再次脑抽晚上过去了。。。。。。</p>\n<p>一个小格子间，一位老师和你谈感情，谈人生，给你看照片，吹对方家庭背景，2 个小时后，谈到要参加会员才可以，我笑着问多少，心里想 3 位数我立马掏了。8800，嗯，八千八，我立刻醒了🙄，说啥也不考虑就走了。</p>\n<p>现在想来，很多话都是在拉近你的距离，降低你的心理防线，可是有句话我觉得还是很有道理，就是如果不跳出正常的工作朋友圈子，又不是大帅比，又不会主动去舔，最后的结局就是父母亲戚的介绍。</p>\n<p>现在也很想扩大自己的交友圈子，苦于没有渠道，周围同学倒是女生基本都结婚了，男的苏州本地人都是单身着😑，大家在 26/27 的时候会着急嘛🤨</p>\n","url":"https://www.v2ex.com/t/589872","replies":57,"created_ts":1565167160,"created":"16:39:20","title":"完了，我也开始焦虑了","author":"scleom","author_url":"https://www.v2ex.com/u/scleom","author_image":"//cdn.v2ex.com/avatar/79fa/4a75/292503_mini.png?m=1564738949"},{"id":589821,"node":"生活","node_url":"https://www.v2ex.com/go/life","node_image":"//cdn.v2ex.com/navatar/6e27/13a6/557_mini.png?m=1473710080","description":"<a target=\"_blank\" href=\"https://i.imgur.com/EAIImB1.png\" rel=\"nofollow\" target=\"_blank\"><img src=\"https://i.imgur.com/EAIImB1.png\" class=\"embedded_image\"></a> <br />  <br />沪苏异地，不能亲临现场，还需要送其他的吗？","url":"https://www.v2ex.com/t/589821","replies":54,"created_ts":1565160634,"created":"14:50:34","title":"七夕给男朋友点了两杯奶茶","author":"zhangmengyu","author_url":"https://www.v2ex.com/u/zhangmengyu","author_image":"//cdn.v2ex.com/avatar/350f/03c3/322386_mini.png?m=1542592046"},{"id":589682,"node":"问与答","node_url":"https://www.v2ex.com/go/qna","node_image":"//cdn.v2ex.com/navatar/c20a/d4d7/12_mini.png?m=1564402099","description":"<p>这两天我一直梦到自己溺水了，然后被喜欢的人刚喜欢不久的人救起来了。请问 V 友们怎么解释，两天同样的梦境，有点吓人啊，</p>\n","url":"https://www.v2ex.com/t/589682","replies":53,"created_ts":1565137767,"created":"08:29:27","title":"这两天一直做梦，而且是同样的梦境","author":"woshi88","author_url":"https://www.v2ex.com/u/woshi88","author_image":"//cdn.v2ex.com/avatar/cfb6/9c4e/409648_mini.png?m=1565159487"},{"id":589681,"node":"程序员","node_url":"https://www.v2ex.com/go/programmer","node_image":"//cdn.v2ex.com/navatar/94f6/d7e0/300_mini.png?m=1565073122","description":"我们开源 IM 放出去一段时间了，star 数一直快速增长。<br /><br />感兴趣的公司越来越多，不断有公司咨询定制等付费服务，聊的都挺好，但到最后谈到支付方式的时候，一听我们是个人，只能向个人转账，然后都没然后了。<br /><br />请问大家，公司一般不和个人进行业务往来吗？这问题如何解决？<br /><br />最后，如果对开源 IM 感兴趣，可以到 github 围观我们：<br /><br /><a target=\"_blank\" href=\"https://github.com/wildfirechat\" rel=\"nofollow\">https://github.com/wildfirechat</a>","url":"https://www.v2ex.com/t/589681","replies":47,"created_ts":1565136583,"created":"08:09:43","title":"难道公司不能和个人有业务往来吗？","author":"imndx","author_url":"https://www.v2ex.com/u/imndx","author_image":"//cdn.v2ex.com/gravatar/ab7122204a1f6b373e304136d3f82f27?s=24&d=retro"}]