[{"id":582864,"node":"问与答","node_url":"https://www.v2ex.com/go/qna","node_image":"//cdn.v2ex.com/navatar/c20a/d4d7/12_mini.png?m=1562041571","description":"","url":"https://www.v2ex.com/t/582864","replies":60,"created_ts":1563093286,"created":"16:34:46","title":"v 友们，上班你们带啥表~","author":"justin2018","author_url":"https://www.v2ex.com/u/justin2018","author_image":"//cdn.v2ex.com/avatar/83e8/4827/351542_mini.png?m=1547034280"},{"id":582873,"node":"问与答","node_url":"https://www.v2ex.com/go/qna","node_image":"//cdn.v2ex.com/navatar/c20a/d4d7/12_mini.png?m=1562041571","description":"已经去了四次了，但是感觉进步比较小。<br /><br />现在我只能憋一口气把脸埋在水里游，不会换气，不会踩水，也许游泳的动作也不是很对。<br /><br />看到很多小朋友可以把头露出水面游，可是我做不到。<br /><br />现在的关键是我想学会怎么换气，看到旁边的教练教小朋友，我就在旁边听着偷师。划水，抬头，换气。可是我抬头换气的时候仓促地吸一口，然后头埋下去就不得不狂吐气，然后结果就是身体下沉。<br /><br />我也去 B 站看过一些视频，但是实际操作呢，或许还是需要人指点，自己去练总是很难学会。<br /><br />所以，我想请大神指点下，我换气埋脸的时候狂吐气，然后身体下沉的原因在哪里？我应该从何练起呢？<br /><br />感谢各位大佬不吝赐教🙏","url":"https://www.v2ex.com/t/582873","replies":49,"created_ts":1563095975,"created":"17:19:35","title":"求大神指教怎么学游泳","author":"AzureTT","author_url":"https://www.v2ex.com/u/AzureTT","author_image":"//cdn.v2ex.com/avatar/2609/73f4/240200_mini.png?m=1547821695"},{"id":582893,"node":"游戏","node_url":"https://www.v2ex.com/go/games","node_image":"//cdn.v2ex.com/navatar/b53b/3a3d/55_mini.png?m=1550138353","description":"这两天在 steam 上玩某横版动作游戏，感觉键盘键位设置十分麻烦，冲动之下入手了 xbox one，想顺手找一些合适的游戏～<br />问题是个人笔记本并非游戏本，风暴英雄最低画质流畅运行的水平= =可能带不动很多适合手柄玩的大作，想求一些“小而美”的游戏……不知道有没有<br />实在不行想入外接显卡的坑了😂","url":"https://www.v2ex.com/t/582893","replies":45,"created_ts":1563102396,"created":"19:06:36","title":"迫于入手了 xbox 手柄，求推荐游戏","author":"RongAi","author_url":"https://www.v2ex.com/u/RongAi","author_image":"//cdn.v2ex.com/gravatar/5e0796f522621b01ff306cf09d17a019?s=24&d=retro"},{"id":582798,"node":"宽带症候群","node_url":"https://www.v2ex.com/go/bb","node_image":"//cdn.v2ex.com/navatar/a3c6/5c29/108_mini.png?m=1562041560","description":"@<a target=\"_blank\" href=\"/member/hlz0812\" rel=\"nofollow\">hlz0812</a><br />近期实在受不了帝都的地铁 15 号线中段（望京-望京西）隧道内无信号的问题，向帝都联通投诉了。他们勘测后表示情况属实，并表示已经现场勘察完毕，据说会在本月底施工，为期 6 个月。有每天路过此地的小伙伴们关注一下吧。有改善请随时报道一下。<br /><br />就有些不明白了，同样的京港 14 号线帝都联通隧道内则无任何问题，信号强度很好，稳定的一批，再反观地铁 15 号线，怎么差别就这么大，从 15 号线 14 年年底开通至今，信号问题一直存在。<br /><br /><img src=\"http://wx3.sinaimg.cn/mw690/549dba2aly1g4z5jtijuej209q0gzt8s.jpg\" class=\"embedded_image\" referrerpolicy=\"no-referrer\"> <br /><img src=\"http://wx4.sinaimg.cn/mw690/549dba2aly1g4z5ju093zj209m0h0mx8.jpg\" class=\"embedded_image\" referrerpolicy=\"no-referrer\"> ","url":"https://www.v2ex.com/t/582798","replies":40,"created_ts":1563070957,"created":"10:22:37","title":"帝都的地铁 15 号线中段（望京-望京西）信号差的可以了，干的漂亮！","author":"bclerdx","author_url":"https://www.v2ex.com/u/bclerdx","author_image":"//cdn.v2ex.com/avatar/fc7d/a860/158781_mini.png?m=1478003368"},{"id":582904,"node":"问与答","node_url":"https://www.v2ex.com/go/qna","node_image":"//cdn.v2ex.com/navatar/c20a/d4d7/12_mini.png?m=1562041571","description":"之前一直都没剪过鼻毛，一直都不会外露尴尬。有一次心血来潮剪了一次，结果现在每周都会露一根出来……为啥咧？","url":"https://www.v2ex.com/t/582904","replies":39,"created_ts":1563105575,"created":"19:59:35","title":"各位老哥，你们是怎么解决鼻毛问题的？","author":"Catal9527","author_url":"https://www.v2ex.com/u/Catal9527","author_image":"//cdn.v2ex.com/avatar/eae2/36ca/421007_mini.png?m=1562745169"},{"id":582858,"node":"问与答","node_url":"https://www.v2ex.com/go/qna","node_image":"//cdn.v2ex.com/navatar/c20a/d4d7/12_mini.png?m=1562041571","description":"只吃早餐和晚餐，现在 160 重，想减到 130。","url":"https://www.v2ex.com/t/582858","replies":37,"created_ts":1563089774,"created":"15:36:14","title":"中午不常吃午饭有影响么","author":"adyyq","author_url":"https://www.v2ex.com/u/adyyq","author_image":"//cdn.v2ex.com/gravatar/80edba21f3c352013acaf86ca4d2fa8c?s=24&d=retro"},{"id":582834,"node":"云计算","node_url":"https://www.v2ex.com/go/cloud","node_image":"//cdn.v2ex.com/navatar/c9e1/074f/104_mini.png?m=1562807272","description":"<h1>如何使用</h1>\n<p>使用 root 登陆后,直接在 shell 里执行</p>\n<pre><code>bash &lt;(curl -s -L https://git.io/fjlXG)\n</code></pre>\n<p>源码<a href=\"https://github.com/bugparty/byebye-aegis\" rel=\"nofollow\">https://github.com/bugparty/byebye-aegis</a></p>\n","url":"https://www.v2ex.com/t/582834","replies":35,"created_ts":1563080310,"created":"12:58:30","title":"一键删除套路云监控脚本分享","author":"fancyhan","author_url":"https://www.v2ex.com/u/fancyhan","author_image":"//cdn.v2ex.com/avatar/b9b3/7cdd/13105_mini.png?m=1555556097"},{"id":582885,"node":"北京","node_url":"https://www.v2ex.com/go/beijing","node_image":"//cdn.v2ex.com/navatar/1f0e/3dad/19_mini.png?m=1559027836","description":"","url":"https://www.v2ex.com/t/582885","replies":34,"created_ts":1563099615,"created":"18:20:15","title":"上午刚买了套房，可以分享些行情","author":"Lavventura","author_url":"https://www.v2ex.com/u/Lavventura","author_image":"//cdn.v2ex.com/avatar/be27/6ed7/208932_mini.png?m=1559551369"},{"id":582780,"node":"Windows","node_url":"https://www.v2ex.com/go/windows","node_image":"//cdn.v2ex.com/navatar/e7b2/4b11/360_mini.png?m=1507538818","description":"<p>i7-9700K+Z390 主板+16G 内存+2080 显卡。SSD 是一个杂牌的 1T+SATA3 接口的 。Windows 是刚全新安装的</p>\n<p>“有点卡”指的是在低负载下执行一些基本操作时仍然有点卡。例如我右键点击任务栏里的窗口图标，它并不是瞬间响应的，而是很明显会卡顿一下，要过个 0.3 秒才会弹出菜单。再例如我双击“此电脑”也会卡顿一下，再出现硬盘图标。我的笔记本就完全不存在这个问题，基本上是瞬间响应，感受不到卡顿</p>\n<p>我能想到的原因就是 SSD 不太彳亍，响应速度慢一拍。所以就想弄一个三星的 PCIE SSD。想问一下还有可能是什么原因？</p>\n","url":"https://www.v2ex.com/t/582780","replies":31,"created_ts":1563056590,"created":"06:23:10","title":"新买的台式机有点卡，会不会是 SSD 的原因？","author":"wallriding","author_url":"https://www.v2ex.com/u/wallriding","author_image":"//cdn.v2ex.com/avatar/eb9f/b3b2/276150_mini.png?m=1513873397"},{"id":582792,"node":"问与答","node_url":"https://www.v2ex.com/go/qna","node_image":"//cdn.v2ex.com/navatar/c20a/d4d7/12_mini.png?m=1562041571","description":"这说明了什么？有人来讲讲吗？","url":"https://www.v2ex.com/t/582792","replies":30,"created_ts":1563067876,"created":"09:31:16","title":"交易区有个人送平板，说取股价的后两位数，但是超过 100 了，后面还是不停有人回复求送。","author":"AzureTT","author_url":"https://www.v2ex.com/u/AzureTT","author_image":"//cdn.v2ex.com/avatar/2609/73f4/240200_mini.png?m=1547821695"},{"id":582774,"node":"瑞典","node_url":"https://www.v2ex.com/go/se","node_image":"//cdn.v2ex.com/navatar/58ae/749f/561_mini.png?m=1360452015","description":"<p>来总部出差一个多月，其实是来避暑的😄<br><br>真的生活很悠闲，就是纬度高，夏天白天长，冬天漫漫黑夜，没有兴趣爱好会很无聊<br><br><img src=\"https://i.loli.net/2019/07/14/5d2a1dc90813f62729.png\" alt=\"V2erForiOS\"><br><img src=\"https://i.loli.net/2019/07/14/5d2a1dd91df5449078.png\" alt=\"V2erForiOS\"><br><img src=\"https://i.loli.net/2019/07/14/5d2a1de4acdf734688.png\" alt=\"V2erForiOS\"><br><img src=\"https://i.loli.net/2019/07/14/5d2a1deab2d3883609.png\" alt=\"V2erForiOS\"><br><img src=\"https://i.loli.net/2019/07/14/5d2a1df57720f41849.png\" alt=\"V2erForiOS\"><br><img src=\"https://i.loli.net/2019/07/14/5d2a1dfc6bfc922022.png\" alt=\"V2erForiOS\"><br></p>\n","url":"https://www.v2ex.com/t/582774","replies":30,"created_ts":1563041336,"created":"02:08:56","title":"来瑞典出差","author":"kljsandjb","author_url":"https://www.v2ex.com/u/kljsandjb","author_image":"//cdn.v2ex.com/avatar/bd76/b399/278144_mini.png?m=1552312974"},{"id":582872,"node":"程序员","node_url":"https://www.v2ex.com/go/programmer","node_image":"//cdn.v2ex.com/navatar/94f6/d7e0/300_mini.png?m=1562807299","description":"<p>总所周知，函数体返回值那里没有&amp;，就会返回一个中间变量。</p>\n<pre><code class=\"language-cpp\">class sale {\npublic:\n\tint i = 1;\n};\n\nsale add(const sale&amp; lift, const sale&amp; right) {\n\tsale sum = lift;\n\tsum.i += right.i;\n\treturn sum;\n}\n\nint main()\n{\n\tsale one;\n\tsale two;\n\tconst sale&amp; global = add(one, two);\n}\n</code></pre>\n<p>假设有如上代码，进行反汇编后，汇编如下：</p>\n<pre><code class=\"language-asm\">\tconst sale&amp; global = add(one, two);\n00D51A32 8D 45 E8             lea         eax,[two]  \n00D51A35 50                   push        eax  \n00D51A36 8D 4D F4             lea         ecx,[one]  \n00D51A39 51                   push        ecx  \n00D51A3A E8 40 F9 FF FF       call        add (0D5137Fh)  \n00D51A3F 83 C4 08             add         esp,8  #调用完毕后，清除栈空间\n00D51A42 89 85 04 FF FF FF    mov         dword ptr [ebp-0FCh],eax  #为中间变量分配空间\n00D51A48 8B 95 04 FF FF FF    mov         edx,dword ptr [ebp-0FCh]  \n00D51A4E 89 55 D0             mov         dword ptr [ebp-30h],edx  #把中间变量复制给新的变量\n00D51A51 8D 45 D0             lea         eax,[ebp-30h]  #导入新变量的地址\n00D51A54 89 45 DC             mov         dword ptr [global],eax  #把这个地址给 global，因为引用本质是指针\n</code></pre>\n<p>上面写的注释不一定对，但为什么这里要分配两次空间呢？\n如果我换一个简单的程序：</p>\n<pre><code class=\"language-cpp\">int re() {\n\treturn 5;\n}\n\nint main()\n{\n\t//int a = 1;\n\tconst int&amp; b = re();\n}\n</code></pre>\n<p>他的汇编就和我想象中一样了，只分配一次空间：</p>\n<pre><code class=\"language-asm\">\tconst int&amp; b = re();\n00B019B2 E8 0E FA FF FF       call        re (0B013C5h)  \n00B019B7 89 45 E8             mov         dword ptr [ebp-18h],eax  #分配空间\n00B019BA 8D 45 E8             lea         eax,[ebp-18h]  #把地址导入 eax\n00B019BD 89 45 F4             mov         dword ptr [b],eax #把 eax 赋值给 b，因为 b 是引用，相当于指针\n</code></pre>\n","url":"https://www.v2ex.com/t/582872","replies":29,"created_ts":1563095240,"created":"17:07:20","title":"同样是 return 一个中间变量，为什么另一种代码的反汇编分配了两次空间？","author":"amiwrong123","author_url":"https://www.v2ex.com/u/amiwrong123","author_image":"//cdn.v2ex.com/avatar/c563/e2bd/417414_mini.png?m=1563098878"},{"id":582850,"node":"问与答","node_url":"https://www.v2ex.com/go/qna","node_image":"//cdn.v2ex.com/navatar/c20a/d4d7/12_mini.png?m=1562041571","description":"<p>CSDN 感觉吃相太难看了。。。</p>\n<p>cnblog、oschina ？大家一般上哪写博客呢？</p>\n","url":"https://www.v2ex.com/t/582850","replies":29,"created_ts":1563086361,"created":"14:39:21","title":"各位老铁们写博客一般在哪写啊？","author":"gramyang","author_url":"https://www.v2ex.com/u/gramyang","author_image":"//cdn.v2ex.com/avatar/6112/d133/314095_mini.png?m=1555035169"},{"id":582802,"node":"Android","node_url":"https://www.v2ex.com/go/android","node_image":"//cdn.v2ex.com/navatar/d67d/8ab4/39_mini.png?m=1562807111","description":"<p>在使用过的国产安卓系统中，发现系统级的搜索(也就是自带浏览器的搜索引擎，同时也是其他快捷搜索入口比如负一屏或者下拉搜索，语音助手搜索)总是那几个，360，百度，神马之类，没法自己选择为 Google 引擎。</p>\n<p>而如果要实现 Google 搜索则需要刷其它区的固件，which 会损失掉许多本地化的功能，比如三星的系统后台自启动管理或是小米的公交卡之类。</p>\n<p>有没有一个国产安卓系统可以自由切换到 Google 搜索而又保留本地化的功能呢？</p>\n","url":"https://www.v2ex.com/t/582802","replies":29,"created_ts":1563072383,"created":"10:46:23","title":"有哪个国产安卓系统可以切换系统级 Google 搜索的？","author":"zshstc","author_url":"https://www.v2ex.com/u/zshstc","author_image":"//cdn.v2ex.com/avatar/c5b0/3cd6/193770_mini.png?m=1538493394"},{"id":582829,"node":"问与答","node_url":"https://www.v2ex.com/go/qna","node_image":"//cdn.v2ex.com/navatar/c20a/d4d7/12_mini.png?m=1562041571","description":"<p>微信交易方不是自己，只是知道交易流水号</p>\n","url":"https://www.v2ex.com/t/582829","replies":28,"created_ts":1563078767,"created":"12:32:47","title":"老哥们，能通过微信的交易流水号，查询到收款方是谁吗？","author":"keepongjl","author_url":"https://www.v2ex.com/u/keepongjl","author_image":"//cdn.v2ex.com/avatar/c768/595f/276047_mini.png?m=1518144357"},{"id":582773,"node":"问与答","node_url":"https://www.v2ex.com/go/qna","node_image":"//cdn.v2ex.com/navatar/c20a/d4d7/12_mini.png?m=1562041571","description":"<p>没喝过想试试，又怕心脏“咚咚咚”。。。<img src=\"https://i.loli.net/2019/07/14/5d2a19cedaaf687711.png\" alt=\"V2erForiOS\"></p>\n","url":"https://www.v2ex.com/t/582773","replies":25,"created_ts":1563040348,"created":"01:52:28","title":"有人喝过魔爪吗？跟红牛比起来，哪个更猛？","author":"Heiban","author_url":"https://www.v2ex.com/u/Heiban","author_image":"//cdn.v2ex.com/avatar/1538/1071/364698_mini.png?m=1542782624"}]